ccrvam/__init__.py
ccrvam/checkerboard/__init__.py
ccrvam/checkerboard/genccrvam.py
ccrvam/checkerboard/genstatsim.py
ccrvam/checkerboard/utils.py
ccrvam-1.2.5.dist-info/licenses/LICENSE
docs/__init__.py
docs/conf.py
tests/__init__.py
tests/test_genccrvam.py
tests/test_genstatsim.py
tests/test_utils.py
ccrvam-1.2.5.dist-info/METADATA
ccrvam-1.2.5.dist-info/WHEEL
ccrvam-1.2.5.dist-info/top_level.txt
ccrvam-1.2.5.dist-info/RECORD
