Metadata-Version: 2.4
Name: ccrvam
Version: 1.2.5
Summary: Python implementation of Checkerboard Copula Regression-based Visualization and Association Measure
Home-page: https://github.com/DhyeyMavani2003/ccrvam
Author: Dhyey Mavani, Daeyoung Kim, Shu-Min Liao
License: GPL-3
Keywords: ccrvam
License-File: LICENSE
Requires-Dist: numpy
Requires-Dist: pandas
Requires-Dist: pytest
Requires-Dist: coverage
Requires-Dist: scipy
Requires-Dist: matplotlib
Dynamic: author
Dynamic: description
Dynamic: description-content-type
Dynamic: home-page
Dynamic: keywords
Dynamic: license
Dynamic: license-file
Dynamic: requires-dist
Dynamic: summary
